fit_resonator/Sdata.py
fit_resonator/__init__.py
fit_resonator/check_data.py
fit_resonator/fit_multiple.py
fit_resonator/functions.py
fit_resonator/resonator.py
scresonators_fit-0.6.1.dist-info/METADATA
scresonators_fit-0.6.1.dist-info/WHEEL
scresonators_fit-0.6.1.dist-info/top_level.txt
scresonators_fit-0.6.1.dist-info/RECORD
