Metadata-Version: 2.1
Name: scresonators-fit
Version: 0.6.1
Summary: Python library for measuring and fitting superconducting resonator data
Home-page: https://github.com/Boulder-Cryogenic-Quantum-Testbed/scresonators
Author: CU Boulder Cryogenic Quantum Testbed
Keywords: scresonators,superconducting resonators,resonator fit
Requires-Python: >=3.7
Requires-Dist: attr (==0.3.*)
Requires-Dist: inflect (==2.1.*)
Requires-Dist: lmfit (==0.9.*)
Requires-Dist: matplotlib (>=3.0.*)
Requires-Dist: numpy (==1.16.*)
Requires-Dist: pandas (==0.24.*)
Requires-Dist: pylabrad (==0.97.*)
Requires-Dist: scipy (==1.3.*)
Requires-Dist: sympy (==1.4.*)
Requires-Dist: scikit-rf (==0.19.*)
